Combinational_Circuits/4.Ripplecarryadder/fulladder.v
module fulladder(a,b,c,s,cout);
    input a,b,c;
    output s,cout;
    wire t1,t2,t3;
    xor g1(t1,a,b), g2(s,t1,c);
    and g3(t2,t1,c), g4(t3,a,b);
    or g5(cout,t2,t3);
endmodule

Combinational_Circuits/2.FullAdder/fulladder_tb.v
`timescale 1ns/1ps

module fulladder_tb;
    reg p,q,r;
    wire sum,c_out;

    fulladder uut (.a(p),.b(q),.c(r),.s(sum),.cout(c_out));
    
    initial
    begin
        $dumpfile("fulladder.vcd");
        $dumpvars(0,fulladder_tb);
        $monitor("Time=%0t|a=%b|b=%b|c=%b|sum=%b|cout=%b",$time,p,q,r,sum,c_out);
        p=0;q=0;r=0;#10;
        p=0;q=0;r=1;#10;
        p=0;q=1;r=0;#10;
        p=0;q=1;r=1;#10;
        p=1;q=0;r=0;#10;
        p=1;q=0;r=1;#10;
        p=1;q=1;r=0;#10;
        p=1;q=1;r=1;#10;

    end

endmodule

Combinational_Circuits/2.FullAdder/fulladder.vcd
$date
	Thu Jan 15 18:47:32 2026
$end
$version
	Icarus Verilog
$end
$timescale
	1ps
$end
$scope module fulladder_tb $end
$var wire 1 ! sum $end
$var wire 1 " c_out $end
$var reg 1 # p $end
$var reg 1 $ q $end
$var reg 1 % r $end
$scope module uut $end
$var wire 1 # a $end
$var wire 1 $ b $end
$var wire 1 % c $end
$var wire 1 " cout $end
$var wire 1 ! s $end
$var wire 1 & t1 $end
$var wire 1 ' t2 $end
$var wire 1 ( t3 $end
$upscope $end
$upscope $end
$enddefinitions $end
$comment Show the parameter values. $end
$dumpall
$end
#0
$dumpvars
0(
0'
0&
0%
0$
0#
0"
0!
$end
#10000
1!
1%
#20000
1&
0%
1$
#30000
1"
0!
1'
1%
#40000
0"
1!
0'
0%
0$
1#
#50000
1"
0!
1'
1%
#60000
0'
0&
1(
0%
1$
#70000
1!
1%
