Combinational_Circuits/6.FullSubtractor/full_sub.v
module full_sub(a,b,c,d,bo);
    input a,b,c;
    output d,bo;
    wire w1,w2,w3;

    xor g1 (w1,a,b); xor g2 (d,w1,c);
    and g3 (w2,~(a),b); and g4 (w3,~w1,c);
    or g5 (bo,w3,w2);
endmodule

Combinational_Circuits/6.FullSubtractor/full_sub_tb.v
`timescale 1ns/1ps;

module full_sub_tb;
    reg a,b,c;
    wire d,bo;

    full_sub uut (.a(a),.b(b),.c(c),.d(d),.bo(bo));

    initial 
    begin 
        $dumpfile("full_sub.vcd");
        $dumpvars(0,full_sub_tb);
        $monitor("t=0%t | a=%b | b=%b | c=%b | d=%b | bo=%b ",$time,a,b,c,d,bo);
        #10
        #10 a=0;b=0;c=0;
        #10 a=0;b=0;c=1;
        #10 a=0;b=1;c=0;
        #10 a=0;b=1;c=1;
        #10 a=1;b=0;c=0;
        #10 a=1;b=0;c=1;
        #10 a=1;b=1;c=0;
        #10 a=1;b=1;c=1;
        #10 $finish;
    end
endmodule

Combinational_Circuits/6.FullSubtractor/full_sub.vcd
$date
	Wed Jan 28 22:09:54 2026
$end
$version
	Icarus Verilog
$end
$timescale
	1ps
$end
$scope module full_sub_tb $end
$var wire 1 ! d $end
$var wire 1 " bo $end
$var reg 1 # a $end
$var reg 1 $ b $end
$var reg 1 % c $end
$scope module uut $end
$var wire 1 # a $end
$var wire 1 $ b $end
$var wire 1 " bo $end
$var wire 1 % c $end
$var wire 1 ! d $end
$var wire 1 & w1 $end
$var wire 1 ' w2 $end
$var wire 1 ( w3 $end
$upscope $end
$upscope $end
$enddefinitions $end
$comment Show the parameter values. $end
$dumpall
$end
#0
$dumpvars
x(
x'
x&
x%
x$
x#
x"
x!
$end
#20000
0"
0!
0(
0'
0&
0%
0$
0#
#30000
1"
1!
1(
1%
#40000
0(
1&
1'
0%
1$
#50000
0!
1%
#60000
0"
1!
0'
0%
0$
1#
#70000
0!
1%
#80000
0&
0%
1$
#90000
1"
1!
1(
1%
