Combinational_Circuits/1.HalfAdder/half_adder.v
module half_adder(a,b,s,c);
    input a,b;
    output s,c;

    assign s=a^b;
    assign c=a&b;
endmodule

Combinational_Circuits/3.FullAdderusinghalf/fa_ha.v
module fa_ha(a,b,cin,s,cout);
    input a,b,cin;
    output s,cout;
    wire s1,w1,w2;

    // First Half adder
    // . port name from the module (signal name from the current module)
    half_adder HA1 (.a(a),.b(b),.s(s1),.c(w1));

    // Second half adder
    half_adder HA2 (.a(s1),.b(cin),.s(s),.c(w2));

    assign cout = w1 | w2;

endmodule

Combinational_Circuits/3.FullAdderusinghalf/fa_ha_tb.v
`timescale 1ns /1ps;

module fa_ha_tb;
    reg a,b,cin;
    wire s,cout;

    fa_ha uut (.a(a),.b(b),.cin(cin),.s(s),.cout(cout));

    initial 
        begin
            $dumpfile("fa_ha.vcd");
            $dumpvars(0,fa_ha_tb);
            $monitor ("t=%0t | a=%b | b=%b | cin=%b | s = %b | cout =%b",$time,a,b,cin,s,cout);
            #10
            a=0;b=0;cin=0;#10
            a=0;b=0;cin=1;#10
            a=0;b=1;cin=0;#10
            a=0;b=1;cin=1;#10
            a=1;b=0;cin=0;#10
            a=1;b=0;cin=1;#10
            a=1;b=1;cin=0;#10
            a=1;b=1;cin=1;#10
            #10 $finish;
        end

endmodule

Combinational_Circuits/3.FullAdderusinghalf/fa_ha.vcd
$date
	Wed Jan 28 12:50:59 2026
$end
$version
	Icarus Verilog
$end
$timescale
	1ps
$end
$scope module fa_ha_tb $end
$var wire 1 ! s $end
$var wire 1 " cout $end
$var reg 1 # a $end
$var reg 1 $ b $end
$var reg 1 % cin $end
$scope module uut $end
$var wire 1 # a $end
$var wire 1 $ b $end
$var wire 1 % cin $end
$var wire 1 " cout $end
$var wire 1 & w2 $end
$var wire 1 ' w1 $end
$var wire 1 ( s1 $end
$var wire 1 ! s $end
$scope module HA1 $end
$var wire 1 # a $end
$var wire 1 $ b $end
$var wire 1 ' c $end
$var wire 1 ( s $end
$upscope $end
$scope module HA2 $end
$var wire 1 ( a $end
$var wire 1 % b $end
$var wire 1 & c $end
$var wire 1 ! s $end
$upscope $end
$upscope $end
$upscope $end
$enddefinitions $end
$comment Show the parameter values. $end
$dumpall
$end
#0
$dumpvars
x(
x'
x&
x%
x$
x#
x"
x!
$end
#10000
0"
0!
0&
0(
0'
0%
0$
0#
#20000
1!
1%
#30000
1(
0%
1$
#40000
1"
0!
1&
1%
#50000
0"
1!
0&
0%
0$
1#
#60000
1"
0!
1&
1%
#70000
0&
0(
1'
0%
1$
#80000
1!
1%
