Assignments/lab1/1.FA_dataflow/RTL/fa_df.v
module fa_df(a_in,b_in,c_in,sum_out,c_out);
    input a_in,b_in,c_in;
    output sum_out,c_out;

    assign sum_out = a_in ^ b_in ^ c_in;
    assign c_out = (a_in & b_in) | (c_in & (a_in ^ b_in));

endmodule

Labs_and_Assignments/lab1_ass1/1.FA_dataflow/tb/fa_df_tb.v
`timescale 1ns/1ps

module fa_df_tb;

reg a, b , c;
wire sum , carry;

fa_df uut (.a_in(a),.b_in(b),.c_in(c),.sum_out(sum),.c_out(carry));

integer i ;

task apply_test;
    input [2:0] test_vector;
    begin
        {a,b,c} = test_vector;
        #10;
    end
endtask

initial 
begin
    $monitor ("Time = %0t | a=%b | b=%b | c=%b | sum=%b | carry=%b ", $time,a,b,c,sum,carry);
    $dumpfile("fa_df.vcd");
    $dumpvars(0,fa_df_tb);

    for (i=0 ; i<8 ; i = i+1)
    begin
        apply_test(i);
    end

    #100 $finish;
end

endmodule

Assignments/lab1/1.FA_dataflow/tb/fa_df.vcd
$date
	Sat Mar  7 18:11:25 2026
$end
$version
	Icarus Verilog
$end
$timescale
	1ps
$end
$scope module fa_df_tb $end
$var wire 1 ! sum $end
$var wire 1 " carry $end
$var reg 1 # a $end
$var reg 1 $ b $end
$var reg 1 % c $end
$var integer 32 & i [31:0] $end
$scope module uut $end
$var wire 1 # a_in $end
$var wire 1 $ b_in $end
$var wire 1 % c_in $end
$var wire 1 " c_out $end
$var wire 1 ! sum_out $end
$upscope $end
$scope task apply_test $end
$var reg 3 ' test_vector [2:0] $end
$upscope $end
$upscope $end
$enddefinitions $end
$comment Show the parameter values. $end
$dumpall
$end
#0
$dumpvars
b0 '
b0 &
0%
0$
0#
0"
0!
$end
#10000
1!
1%
b1 '
b1 &
#20000
1!
1$
0%
b10 '
b10 &
#30000
1"
0!
1%
b11 '
b11 &
#40000
0"
1!
1#
0$
0%
b100 '
b100 &
#50000
1"
0!
1%
b101 '
b101 &
#60000
0!
1$
0%
b110 '
b110 &
#70000
1!
1%
b111 '
b111 &
#80000
b1000 &
